th_spiderman
