Metadata-Version: 2.1
Name: th-spiderman
Version: 0.3
Summary: Drawing Tom Holland
Author-email: erdauletov.1512@gmail.com
